MANIFEST.in
README
setup.py
trustedanalytics/__init__.py
trustedanalytics.egg-info/PKG-INFO
trustedanalytics.egg-info/SOURCES.txt
trustedanalytics.egg-info/dependency_links.txt
trustedanalytics.egg-info/requires.txt
trustedanalytics.egg-info/top_level.txt
trustedanalytics/core/.gitignore
trustedanalytics/core/__init__.py
trustedanalytics/core/admin.py
trustedanalytics/core/aggregation.py
trustedanalytics/core/api.py
trustedanalytics/core/atkpandas.py
trustedanalytics/core/atktypes.py
trustedanalytics/core/classifymetrics.py
trustedanalytics/core/clusteringcoefficient.py
trustedanalytics/core/column.py
trustedanalytics/core/datacatalog.py
trustedanalytics/core/decorators.py
trustedanalytics/core/docstubs1.py
trustedanalytics/core/docstubs2.py
trustedanalytics/core/errorhandle.py
trustedanalytics/core/files.py
trustedanalytics/core/frame.py
trustedanalytics/core/graph.py
trustedanalytics/core/histogram.py
trustedanalytics/core/loggers.py
trustedanalytics/core/logisticregression.py
trustedanalytics/core/model.py
trustedanalytics/core/row.py
trustedanalytics/core/ui.py
trustedanalytics/doc/__init__.py
trustedanalytics/doc/build_docs.py
trustedanalytics/doc/pyrst.py
trustedanalytics/doc/restrst.py
trustedanalytics/doc/python_api/connect.rst
trustedanalytics/doc/python_api/index.rst
trustedanalytics/doc/python_api/datasources/index.rst
trustedanalytics/doc/python_api/datatypes/index.rst
trustedanalytics/doc/python_api/frames/.gitignore
trustedanalytics/doc/python_api/graphs/.gitignore
trustedanalytics/doc/python_api/models/.gitignore
trustedanalytics/doc/rest_api/v1/index.rst
trustedanalytics/doc/rest_api/v1/info.rst
trustedanalytics/doc/rest_api/v1/commands/about_command_names.rst
trustedanalytics/doc/rest_api/v1/commands/command_full_name.png
trustedanalytics/doc/rest_api/v1/commands/get_command.rst
trustedanalytics/doc/rest_api/v1/commands/index.rst
trustedanalytics/doc/rest_api/v1/commands/issue_command.rst
trustedanalytics/doc/rest_api/v1/entities/create_entity.rst
trustedanalytics/doc/rest_api/v1/entities/drop_entity.rst
trustedanalytics/doc/rest_api/v1/entities/get_entity.rst
trustedanalytics/doc/rest_api/v1/entities/get_frame_data.rst
