Metadata-Version: 1.0
Name: trustedanalytics
Version: 0.6.0.post2016012510686
Summary: Trusted Analytics Toolkit
Home-page: http://trustedanalytics.github.io/atk
Author: trustedanalytics
Author-email: UNKNOWN
License: Apache 2
Keywords: analytics big data yarn cloudera hadoop hdfs spark
Platform: UNKNOWN
